[
    {
        "question": "What is CIDI?",
        "answer": "CIDI is a non governmental organisation based in Tanzania mainland. Its main activities are improvement of education and agricultural development."
    },
    {
        "question": "How to Donate?",
        "answer": "One can donate through cash or mobile Money transfers, Bank transfer, Credit cards, Cheque, Visa and MasterCards"
    },
    {
        "question": "Become a Volunteer?",
        "answer": "One can volunteer by filling the form on the website and sharing with us your CV so that we can get to know you better. We encourage volunteers from the age of 20 and above."
    }
]